odoo9_addon_medical_pathology-9.0.1.0.1.99.dev8-py2.7-nspkg.pth
odoo9_addon_medical_pathology-9.0.1.0.1.99.dev8.dist-info/DESCRIPTION.rst
odoo9_addon_medical_pathology-9.0.1.0.1.99.dev8.dist-info/METADATA
odoo9_addon_medical_pathology-9.0.1.0.1.99.dev8.dist-info/RECORD
odoo9_addon_medical_pathology-9.0.1.0.1.99.dev8.dist-info/WHEEL
odoo9_addon_medical_pathology-9.0.1.0.1.99.dev8.dist-info/metadata.json
odoo9_addon_medical_pathology-9.0.1.0.1.99.dev8.dist-info/namespace_packages.txt
odoo9_addon_medical_pathology-9.0.1.0.1.99.dev8.dist-info/top_level.txt
odoo_addons/medical_pathology/README.rst
odoo_addons/medical_pathology/__init__.py
odoo_addons/medical_pathology/__openerp__.py
odoo_addons/medical_pathology/data/medical_pathology_code_type.xml
odoo_addons/medical_pathology/demo/medical_pathology_category_demo.xml
odoo_addons/medical_pathology/demo/medical_pathology_demo.xml
odoo_addons/medical_pathology/demo/medical_pathology_group_demo.xml
odoo_addons/medical_pathology/i18n/es_CO.po
odoo_addons/medical_pathology/i18n/pt_BR.po
odoo_addons/medical_pathology/models/__init__.py
odoo_addons/medical_pathology/models/medical_pathology.py
odoo_addons/medical_pathology/models/medical_pathology_category.py
odoo_addons/medical_pathology/models/medical_pathology_code_type.py
odoo_addons/medical_pathology/models/medical_pathology_group.py
odoo_addons/medical_pathology/security/ir.model.access.csv
odoo_addons/medical_pathology/static/description/icon.png
odoo_addons/medical_pathology/static/description/screenshot_pathologies.png
odoo_addons/medical_pathology/static/description/screenshot_pathology_categories.png
odoo_addons/medical_pathology/tests/__init__.py
odoo_addons/medical_pathology/tests/test_medical_pathology.py
odoo_addons/medical_pathology/tests/test_medical_pathology_category.py
odoo_addons/medical_pathology/tests/test_medical_pathology_group.py
odoo_addons/medical_pathology/views/medical_menu.xml
odoo_addons/medical_pathology/views/medical_pathology_category_view.xml
odoo_addons/medical_pathology/views/medical_pathology_group_view.xml
odoo_addons/medical_pathology/views/medical_pathology_view.xml
