Metadata-Version: 2.0
Name: odoo9-addon-medical-pathology
Version: 9.0.1.0.1.99.dev8
Summary: Extends Odoo Medical with pathologies (diseases).
Home-page: https://laslabs.com/
Author: LasLabs, ACSONE SA/NV, Odoo Community Association (OCA)
Author-email: support@odoo-community.org
License: GPL-3
Platform: UNKNOWN
Classifier: Programming Language :: Python
Classifier: Framework :: Odoo
Classifier: License :: OSI Approved :: GNU General Public License v3 (GPLv3)
Requires-Python: ~=2.7
Requires-Dist: odoo (<9.1a,>=9.0a)
Requires-Dist: odoo9-addon-medical
